[
  {
    "scalp_mode": "reversal",
    "shock_window_seconds": 5.0,
    "tail_prob": 0.02,
    "min_move_bps": 2.0,
    "directional_ratio": 0.6,
    "max_spread_ticks": 1.0,
    "hold_seconds": 5.0,
    "take_profit_ticks": 10.0,
    "stop_loss_ticks": 8.0,
    "reversal_confirm_seconds": 2.0,
    "reversal_retrace_ratio": 0.5,
    "avoid_session_close_seconds": 90.0,
    "order_type": "limit",
    "price_field": "mid_price",
    "limit_mode": "better_ticks",
    "limit_ticks": 1.0,
    "net_pnl": -1263.58249918609,
    "final_pnl": -1263.5824999993201,
    "gross_pnl": -449.9999999996726,
    "commission": 813.5824991864174,
    "frozen_margin": 0.0,
    "trades": 24,
    "win_rate": 0.375,
    "profit_factor": 0.33560759633399123,
    "max_trade_drawdown": -1307.210999382584,
    "au_pnl": -679.9999996796724,
    "ag_pnl": -583.5824995064174,
    "max_hold_seconds": 5.5,
    "avg_hold_seconds": 4.354166666666667,
    "score": 1636.4060001546939,
    "seconds": 45.672
  },
  {
    "scalp_mode": "reversal",
    "shock_window_seconds": 5.0,
    "tail_prob": 0.005,
    "min_move_bps": 1.0,
    "directional_ratio": 0.55,
    "max_spread_ticks": 2.0,
    "hold_seconds": 8.0,
    "take_profit_ticks": 4.0,
    "stop_loss_ticks": 8.0,
    "reversal_confirm_seconds": 2.0,
    "reversal_retrace_ratio": 0.35,
    "avoid_session_close_seconds": 90.0,
    "order_type": "limit",
    "price_field": "mid_price",
    "limit_mode": "worse_ticks",
    "limit_ticks": 0.0,
    "net_pnl": -3525.94224867893,
    "final_pnl": -3525.9422500001965,
    "gross_pnl": -2204.9999999998727,
    "commission": 1320.9422486790577,
    "frozen_margin": 0.0,
    "trades": 40,
    "win_rate": 0.45,
    "profit_factor": 0.21862572179259937,
    "max_trade_drawdown": -3287.4182487074536,
    "au_pnl": -1659.9999994798725,
    "ag_pnl": -1865.9422491990576,
    "max_hold_seconds": 7.0,
    "avg_hold_seconds": 3.125,
    "score": 865.1743128230383,
    "seconds": 72.721
  },
  {
    "scalp_mode": "reversal",
    "shock_window_seconds": 5.0,
    "tail_prob": 0.005,
    "min_move_bps": 2.0,
    "directional_ratio": 0.65,
    "max_spread_ticks": 2.0,
    "hold_seconds": 8.0,
    "take_profit_ticks": 10.0,
    "stop_loss_ticks": 6.0,
    "reversal_confirm_seconds": 2.5,
    "reversal_retrace_ratio": 0.5,
    "order_type": "limit",
    "price_field": "mid_price",
    "limit_mode": "better_ticks",
    "limit_ticks": 1.0,
    "net_pnl": -1954.4459996154949,
    "final_pnl": -1954.4459999997634,
    "gross_pnl": -1569.9999999999409,
    "commission": 384.445999615554,
    "frozen_margin": 0.0,
    "trades": 11,
    "win_rate": 0.18181818181818182,
    "profit_factor": 0.044116384837586675,
    "max_trade_drawdown": -1925.5679996443728,
    "au_pnl": -1139.9999997999407,
    "ag_pnl": -814.445999815554,
    "max_hold_seconds": 8.5,
    "avg_hold_seconds": 2.8636363636363638,
    "score": -219.5240908200659,
    "seconds": 74.413
  },
  {
    "scalp_mode": "reversal",
    "shock_window_seconds": 8.0,
    "tail_prob": 0.005,
    "min_move_bps": 1.5,
    "directional_ratio": 0.7,
    "max_spread_ticks": 2.0,
    "hold_seconds": 5.0,
    "take_profit_ticks": 3.0,
    "stop_loss_ticks": 10.0,
    "reversal_confirm_seconds": 1.0,
    "reversal_retrace_ratio": 0.65,
    "avoid_session_close_seconds": 90.0,
    "order_type": "limit",
    "price_field": "mid_price",
    "limit_mode": "worse_ticks",
    "limit_ticks": 0.0,
    "net_pnl": 80.00000004011824,
    "final_pnl": 80.00000000011642,
    "gross_pnl": 120.00000000011823,
    "commission": 39.99999996,
    "frozen_margin": 0.0,
    "trades": 1,
    "win_rate": 1.0,
    "profit_factor": 0.0,
    "max_trade_drawdown": 0.0,
    "au_pnl": 80.00000004011824,
    "ag_pnl": 0.0,
    "max_hold_seconds": 3.0,
    "avg_hold_seconds": 3.0,
    "score": -1e+18,
    "seconds": 72.505
  },
  {
    "scalp_mode": "reversal",
    "shock_window_seconds": 8.0,
    "tail_prob": 0.002,
    "min_move_bps": 2.0,
    "directional_ratio": 0.6,
    "max_spread_ticks": 2.0,
    "hold_seconds": 3.0,
    "take_profit_ticks": 3.0,
    "stop_loss_ticks": 6.0,
    "reversal_confirm_seconds": 1.0,
    "reversal_retrace_ratio": 0.5,
    "avoid_session_close_seconds": 90.0,
    "order_type": "limit",
    "price_field": "mid_price",
    "limit_mode": "better_ticks",
    "limit_ticks": 0.0,
    "net_pnl": 0.0,
    "final_pnl": 0.0,
    "gross_pnl": 0.0,
    "commission": 0.0,
    "frozen_margin": 0.0,
    "trades": 0,
    "win_rate": 0.0,
    "profit_factor": 0.0,
    "max_trade_drawdown": 0.0,
    "score": -1e+18,
    "seconds": 73.601
  }
]